LICENSE
MANIFEST.in
README.rst
setup.py
arrayfields/__init__.py
arrayfields/fields.py
arrayfields/models.py
django_arrayfields.egg-info/PKG-INFO
django_arrayfields.egg-info/SOURCES.txt
django_arrayfields.egg-info/dependency_links.txt
django_arrayfields.egg-info/not-zip-safe
django_arrayfields.egg-info/top_level.txt